Metadata-Version: 2.1
Name: slicereg
Version: 0.0.1a0
Summary: Registration of 2D sections to a 3D volume
Home-page: https://github.com/adamltyson/slicereg
Author: Adam Tyson, Paul Brodersen
Author-email: adam.tyson@ucl.ac.uk
License: UNKNOWN
Platform: UNKNOWN
Classifier: Development Status :: 3 - Alpha
Classifier: Operating System :: POSIX :: Linux
Classifier: Programming Language :: Python
Classifier: Programming Language :: Python :: 3.6
Classifier: Programming Language :: Python :: 3.7
Classifier: Programming Language :: Python :: 3.8
Classifier: Intended Audience :: Developers
Classifier: Intended Audience :: Science/Research
Requires-Python: >=3.6
Provides-Extra: dev
